LICENSE
MANIFEST.in
README.rst
requirements.txt
setup.py
eolas/__init__.py
eolas/instructions.py
eolas/interpreter.py
eolas/lexer.py
eolas/parser.py
eolas/parsetab.py
eolas.egg-info/PKG-INFO
eolas.egg-info/SOURCES.txt
eolas.egg-info/dependency_links.txt
eolas.egg-info/entry_points.txt
eolas.egg-info/requires.txt
eolas.egg-info/top_level.txt