Metadata-Version: 1.1
Name: eolas
Version: 0.1.0
Summary: Eolas interpreter
Home-page: https://github.com/bfontaine/eolas
Author: Baptiste Fontaine
Author-email: b@ptistefontaine.fr
License: Copyright © 2017 – Baptiste Fontaine
